digitalguide/WhatsAppUpdate.py
digitalguide/__init__.py
digitalguide/db_objects.py
digitalguide/generateActions.py
digitalguide/generateStates.py
digitalguide/pattern.py
digitalguide/send_utils.py
digitalguide/special_actions/__init__.py
digitalguide/special_actions/contextActions.py
digitalguide/special_actions/imageActions.py
digitalguide/special_actions/listenfrageActions.py
digitalguide/special_actions/schaetzfragenActions.py
digitalguide/special_actions/writeActions.py
digitalguide-0.0.524.dist-info/licenses/LICENSE
digitalguide-0.0.524.dist-info/METADATA
digitalguide-0.0.524.dist-info/WHEEL
digitalguide-0.0.524.dist-info/top_level.txt
digitalguide-0.0.524.dist-info/RECORD
