Metadata-Version: 2.4
Name: digitalguide
Version: 0.0.524
Summary: A Python Library to write digital guides for telegram
Author: Soeren Etler
License: MIT
License-File: LICENSE
Requires-Dist: requests
Requires-Dist: redis
Provides-Extra: test
Requires-Dist: pytest; extra == "test"
Requires-Dist: flake8; extra == "test"
Requires-Dist: google-api-python-client; extra == "test"
Requires-Dist: google-auth-httplib2; extra == "test"
Requires-Dist: google-auth-oauthlib; extra == "test"
Requires-Dist: flask; extra == "test"
Requires-Dist: boto3; extra == "test"
Requires-Dist: Pillow; extra == "test"
Requires-Dist: PyYAML; extra == "test"
Provides-Extra: full
Requires-Dist: pymongo[srv]; extra == "full"
Requires-Dist: mongoengine; extra == "full"
Requires-Dist: heyoo; extra == "full"
Dynamic: author
Dynamic: description
Dynamic: description-content-type
Dynamic: license
Dynamic: license-file
Dynamic: provides-extra
Dynamic: requires-dist
Dynamic: summary
